{"id":"OJyE","dependencies":[{"name":"C:\\Users\\Lars\\Desktop\\Polyeco\\visitor\\package.json","includedInParent":true,"mtime":1545313051412}],"generated":{"js":"module.exports=\"5d9d23b09c2fdccdcb21971e47f8c46f.png\";","map":{"mappings":[{"source":"0","name":"module","original":{"line":1,"column":0},"generated":{"line":1,"column":0}},{"source":"0","name":"exports","original":{"line":1,"column":7},"generated":{"line":1,"column":7}},{"source":"0","original":{"line":1,"column":17},"generated":{"line":1,"column":15}}],"sources":{},"lineCount":null}},"hash":"0ec3ab75020104002c25bd918ddf8232","cacheData":{"env":{}}}